{
  "dialogue_id": "slack_export_user_study1",
  "requirements": [
    {
      "id": "r1",
      "is_dismissed": false,
      "dismissed_by_action_ids": [],
      "dismissed_at_turn": null,
      "is_executed": true
    },
    {
      "id": "r2",
      "is_dismissed": false,
      "dismissed_by_action_ids": [],
      "dismissed_at_turn": null,
      "is_executed": false
    },
    {
      "id": "r3",
      "is_dismissed": false,
      "dismissed_by_action_ids": [],
      "dismissed_at_turn": null,
      "is_executed": false
    },
    {
      "id": "r4",
      "is_dismissed": false,
      "dismissed_by_action_ids": [],
      "dismissed_at_turn": null,
      "is_executed": false
    },
    {
      "id": "r5",
      "is_dismissed": false,
      "dismissed_by_action_ids": [],
      "dismissed_at_turn": null,
      "is_executed": false
    },
    {
      "id": "r6",
      "is_dismissed": false,
      "dismissed_by_action_ids": [],
      "dismissed_at_turn": null,
      "is_executed": true
    },
    {
      "id": "r7",
      "is_dismissed": false,
      "dismissed_by_action_ids": [],
      "dismissed_at_turn": null,
      "is_executed": true
    },
    {
      "id": "r8",
      "is_dismissed": false,
      "dismissed_by_action_ids": [],
      "dismissed_at_turn": null,
      "is_executed": false
    },
    {
      "id": "r9",
      "is_dismissed": false,
      "dismissed_by_action_ids": [],
      "dismissed_at_turn": null,
      "is_executed": false
    },
    {
      "id": "r10",
      "is_dismissed": false,
      "dismissed_by_action_ids": [],
      "dismissed_at_turn": null,
      "is_executed": false
    },
    {
      "id": "r11",
      "is_dismissed": false,
      "dismissed_by_action_ids": [],
      "dismissed_at_turn": null,
      "is_executed": false
    },
    {
      "id": "r12",
      "is_dismissed": false,
      "dismissed_by_action_ids": [],
      "dismissed_at_turn": null,
      "is_executed": false
    }
  ]
}